LICENSE
README.md
setup.py
diffsynth/__init__.py
diffsynth/configs/__init__.py
diffsynth/configs/model_config.py
diffsynth/controlnets/__init__.py
diffsynth/controlnets/controlnet_unit.py
diffsynth/controlnets/processors.py
diffsynth/data/__init__.py
diffsynth/data/simple_text_image.py
diffsynth/data/video.py
diffsynth/distributed/__init__.py
diffsynth/distributed/xdit_context_parallel.py
diffsynth/extensions/__init__.py
diffsynth/extensions/ESRGAN/__init__.py
diffsynth/extensions/FastBlend/__init__.py
diffsynth/extensions/FastBlend/api.py
diffsynth/extensions/FastBlend/cupy_kernels.py
diffsynth/extensions/FastBlend/data.py
diffsynth/extensions/FastBlend/patch_match.py
diffsynth/extensions/FastBlend/runners/__init__.py
diffsynth/extensions/FastBlend/runners/accurate.py
diffsynth/extensions/FastBlend/runners/balanced.py
diffsynth/extensions/FastBlend/runners/fast.py
diffsynth/extensions/FastBlend/runners/interpolation.py
diffsynth/extensions/ImageQualityMetric/__init__.py
diffsynth/extensions/ImageQualityMetric/aesthetic.py
diffsynth/extensions/ImageQualityMetric/clip.py
diffsynth/extensions/ImageQualityMetric/config.py
diffsynth/extensions/ImageQualityMetric/hps.py
diffsynth/extensions/ImageQualityMetric/imagereward.py
diffsynth/extensions/ImageQualityMetric/mps.py
diffsynth/extensions/ImageQualityMetric/pickscore.py
diffsynth/extensions/ImageQualityMetric/BLIP/__init__.py
diffsynth/extensions/ImageQualityMetric/BLIP/blip.py
diffsynth/extensions/ImageQualityMetric/BLIP/blip_pretrain.py
diffsynth/extensions/ImageQualityMetric/BLIP/med.py
diffsynth/extensions/ImageQualityMetric/BLIP/vit.py
diffsynth/extensions/ImageQualityMetric/open_clip/__init__.py
diffsynth/extensions/ImageQualityMetric/open_clip/coca_model.py
diffsynth/extensions/ImageQualityMetric/open_clip/constants.py
diffsynth/extensions/ImageQualityMetric/open_clip/factory.py
diffsynth/extensions/ImageQualityMetric/open_clip/generation_utils.py
diffsynth/extensions/ImageQualityMetric/open_clip/hf_configs.py
diffsynth_ybh_sources.egg-info/PKG-INFO
diffsynth_ybh_sources.egg-info/SOURCES.txt
diffsynth_ybh_sources.egg-info/dependency_links.txt
diffsynth_ybh_sources.egg-info/requires.txt
diffsynth_ybh_sources.egg-info/top_level.txt